{
  "intents": [
    {
      "tag": "greeting",
      "patterns": [
        "Hi",
        "Hey",
        "Is anyone there?",
        "Hello"
      ],
      "responses": [
        "Hey :-)",
        "Hello, thanks for chatting",
        "Hi there, what can I do for you?",
        "Hi there, how can I help?"
      ]
    },
    {
      "tag": "howareyou",
      "patterns": [
        "How's it going?",
        "How have you been?",
        "How are things with you?",
        "How are you feeling?",
        "What's up?",
        "How are things?",
        "How's everything?",
        "How have you been doing?",
        "How's life treating you?",
        "How's your day going so far?"
      ],
      "responses": [
        "I'm good, thanks.",
        "I'm doing well, thanks for asking.",
        "Just fine, thanks.",
        "Not too bad, how about you?",
        "Can't complain, how about you?",
        "Pretty good, how about you?",
        "So-so, how are you?",
        "I'm fantastic, thanks!",
        "Could be better, but I'm hanging in there. How about you?",
        "I've been better, but I'm managing."
      ]
    },
    {
      "tag": "whatswrong",
      "patterns": [
        "Is something bothering you?",
        "What's the matter?",
        "What's bothering you?",
        "Something on your mind?",
        "What's the issue?",
        "What's the problem?",
        "What's happened?",
        "What's wrong?",
        "What's going on?",
        "What happened?"
    ],
      "responses": [
        "Nothing, just tired.",
        "Just a long day, thanks for asking.",
        "Nothing much, how about you?",
        "Just feeling overwhelmed, but I'll be okay.",
        "Just some stress at work, nothing to worry about.",
        "A family member is going through a tough time.",
        "I'm just feeling a bit down today.",
        "Just some personal stuff I'm dealing with.",
        "Had a fight with a friend, but we'll work it out.",
        "Just feeling a bit under the weather."
      ]
    },
    {
      "tag": "sorry",
      "patterns": [
        "I'm sorry.",
        "My apologies.",
        "I apologize.",
        "Pardon me.",
        "Excuse me.",
        "Sorry about that.",
        "My bad.",
        "Forgive me.",
        "I feel terrible.",
        "I regret it."
      ],
      "responses": [
        "It's okay.",
        "No problem.",
        "Don't worry about it.",
        "I forgive you.",
        "No need to apologize.",
        "It happens to the best of us.",
        "It's not a big deal.",
        "No harm done.",
        "No worries.",
        "That's alright."
      ]
    },
    {
      "tag": "userIsDoingGood",
      "patterns": [
        "I'm good, thanks.",
        "I'm doing well, thanks for asking.",
        "Just fine, thanks.",
        "Not too bad, how about you?",
        "Can't complain, how about you?",
        "Pretty good, how about you?",
        "I'm fantastic, thanks!",
        "I am doing good"
      ],
      "responses": [
        "That's great!",
        "Glad to hear it!",
        "Awesome!",
        "That's good news!",
        "I'm happy for you!",
        "Fantastic!",
        "Super!",
        "That's fantastic!",
        "Glad to hear you're doing well!",
        "Awesome, keep it up!"
      ]
    },
    {
      "tag": "userIsDoingBad",
      "patterns": [
        "I'm not doing so great",
        "I'm having a rough time",
        "Things are not going well for me",
        "I'm feeling down",
        "Life's been a bit of a struggle lately",
        "I'm not in a good place right now",
        "I've been struggling lately",
        "It's been a tough period for me",
        "I'm not feeling very positive at the moment",
        "I've hit a bit of a low point"
      ],
      "responses": [
        "I'm sorry to hear that.",
        "That's tough. I'm here for you if you need to talk.",
        "It's okay to not be okay. Just take it one day at a time.",
        "I hope things get better for you soon.",
        "Remember that this too shall pass.",
        "I can tell you a joke to brighten your day?",
        "Let me tell you a joke to take your mind off things.",
        "You don't have to face this alone. I'm here for you."
      ]
    },
    {
      "tag": "goodbye",
      "patterns": ["Bye",
        "See you later",
        "Goodbye"
      ],
      "responses": [
        "See you later, thanks for chatting",
        "Have a nice day",
        "Bye! Let's talk again soon."
      ]
    },
    {
      "tag": "thanks",
      "patterns": ["Thanks", "Thank you", "That's helpful", "Thanks a lot!"],
      "responses": ["Happy to help!", "Any time!", "My pleasure"]
    },
    {
      "tag": "funny",
      "patterns": [
        "Tell me a joke!",
        "Tell me something funny!",
        "Do you know a joke?"
      ],
      "responses": [
        "Why did the hipster burn his mouth? He drank the coffee before it was cool.",
        "What did the buffalo say when his son left for college? Bison.",
        "My wife said I should do lunges to stay in shape. That would be a big step forward.",
        "Singing in the shower is fun until you get soap in your mouth. Then it's a soap opera.",
        "I asked my dog what's two minus two. He said nothing.",
        "Why can't a nose be 12 inches long? Because then it would be a foot.",
        "Shout out to my fingers. I can count on all of them."
      ]
    },

    {
      "tag": "Praise",
      "patterns": [
        "That was good"

      ],
      "responses": [
      ]
    },
    {
      "tag": "help",
      "patterns": [
        "What are my options?",
        "What can I choose from?",
        "Can you give me some choices?",
        "What are my choices?",
        "Can you help me?",
        "I need help",
        "help"
      ],
      "responses": [
        "Certainly, here are some options: Click dog, click cat, or keep talking to me",
        "You can choose from the following: Click dog, click cat, or keep talking to me.",
        "There are several options available: Click dog, click cat, or keep talking to me"
      ]
    }
  ]
}